dimapomogiii/__init__.py
dimapomogiii/main.py
dimapomogiii-0.0.1.dist-info/METADATA
dimapomogiii-0.0.1.dist-info/WHEEL
dimapomogiii-0.0.1.dist-info/licenses/LICENSE
dimapomogiii-0.0.1.dist-info/RECORD
