Metadata-Version: 2.3
Name: dimapomogiii
Version: 0.0.1
Summary: descr
Author-email: mvnt <skip@m.r>
License-File: LICENSE
Classifier: License :: OSI Approved :: MIT License
Classifier: Operating System :: OS Independent
Classifier: Programming Language :: Python :: 3
Requires-Python: >=3.10.0
